mem0llama/__init__.py
mem0llama/client/__init__.py
mem0llama/client/main.py
mem0llama/configs/__init__.py
mem0llama/configs/base.py
mem0llama/configs/prompts.py
mem0llama/configs/embeddings/__init__.py
mem0llama/configs/embeddings/base.py
mem0llama/configs/llms/__init__.py
mem0llama/configs/llms/base.py
mem0llama/configs/vector_stores/__init__.py
mem0llama/configs/vector_stores/azure_ai_search.py
mem0llama/configs/vector_stores/chroma.py
mem0llama/configs/vector_stores/elasticsearch.py
mem0llama/configs/vector_stores/milvus.py
mem0llama/configs/vector_stores/opensearch.py
mem0llama/configs/vector_stores/pgvector.py
mem0llama/configs/vector_stores/qdrant.py
mem0llama/configs/vector_stores/redis.py
mem0llama/configs/vector_stores/supabase.py
mem0llama/configs/vector_stores/vertex_ai_vector_search.py
mem0llama/embeddings/__init__.py
mem0llama/embeddings/azure_openai.py
mem0llama/embeddings/base.py
mem0llama/embeddings/configs.py
mem0llama/embeddings/gemini.py
mem0llama/embeddings/huggingface.py
mem0llama/embeddings/ollama.py
mem0llama/embeddings/openai.py
mem0llama/embeddings/together.py
mem0llama/embeddings/vertexai.py
mem0llama/llms/__init__.py
mem0llama/llms/anthropic.py
mem0llama/llms/aws_bedrock.py
mem0llama/llms/azure_openai.py
mem0llama/llms/azure_openai_structured.py
mem0llama/llms/base.py
mem0llama/llms/configs.py
mem0llama/llms/deepseek.py
mem0llama/llms/gemini.py
mem0llama/llms/groq.py
mem0llama/llms/litellm.py
mem0llama/llms/ollama.py
mem0llama/llms/openai.py
mem0llama/llms/openai_structured.py
mem0llama/llms/together.py
mem0llama/llms/xai.py
mem0llama/llms/utils/__init__.py
mem0llama/llms/utils/functions.py
mem0llama/memory/__init__.py
mem0llama/memory/base.py
mem0llama/memory/graph_memory.py
mem0llama/memory/llm_formatter.py
mem0llama/memory/main.py
mem0llama/memory/models.py
mem0llama/memory/setup.py
mem0llama/memory/storage.py
mem0llama/memory/utils.py
mem0llama/proxy/__init__.py
mem0llama/proxy/main.py
mem0llama/vector_stores/__init__.py
mem0llama-0.1.3.dist-info/LICENSE
mem0llama-0.1.3.dist-info/METADATA
mem0llama-0.1.3.dist-info/WHEEL
mem0llama-0.1.3.dist-info/top_level.txt
mem0llama-0.1.3.dist-info/RECORD
