Metadata-Version: 2.2
Name: mem0llama
Version: 0.1.3
Summary: A specialized fork of Mem0 optimized for small, local Large Language Models (LLMs) running through Ollama.
Home-page: https://github.com/alfredwallace7/mem0llama
Author: Alfred WALLACE
Author-email: alfred.wallace@netcraft.fr
License: Apache-2.0
Keywords: memory,llm,ai,agents,qdrant,neo4j,ollama
Classifier: Programming Language :: Python :: 3
Classifier: License :: OSI Approved :: Apache Software License
Classifier: Operating System :: OS Independent
Requires-Python: >=3.9, <4.0
License-File: LICENSE
Requires-Dist: qdrant-client>=1.9.1
Requires-Dist: pydantic>=2.7.3
Requires-Dist: openai>=1.33.0
Requires-Dist: pytz>=2024.1
Requires-Dist: sqlalchemy>=2.0.31
Requires-Dist: langchain-community>=0.3.1
Requires-Dist: langchain-neo4j>=0.3.1
Requires-Dist: rank-bm25>=0.2.2
Requires-Dist: psycopg2-binary>=2.9.10
Requires-Dist: python-dotenv>=1.0.0
Requires-Dist: litellm>=1.0.0
Requires-Dist: rich>=13.0.0
Requires-Dist: ollama>=0.1.0
Dynamic: author
Dynamic: author-email
Dynamic: classifier
Dynamic: home-page
Dynamic: keywords
Dynamic: license
Dynamic: requires-dist
Dynamic: requires-python
Dynamic: summary
